virtnet/__init__.py
virtnet/address.py
virtnet/container.py
virtnet/context.py
virtnet/host.py
virtnet/interface.py
virtnet/iproute.py
virtnet/sched_netem_test.py
virtnet/switch.py
virtnet/syscalls.py
py_virtnet-1.0.1.dist-info/LICENSE
py_virtnet-1.0.1.dist-info/METADATA
py_virtnet-1.0.1.dist-info/WHEEL
py_virtnet-1.0.1.dist-info/top_level.txt
py_virtnet-1.0.1.dist-info/RECORD
