Metadata-Version: 2.1
Name: py-virtnet
Version: 1.0.1
Summary: A library for building testnetworks
Home-page: https://github.com/CN-TU/py-virtnet
Author: Gernot Vormayr
Author-email: gvormayr@gmail.com
License: GPLv2
Platform: UNKNOWN
Classifier: Development Status :: 5 - Production/Stable
Classifier: Intended Audience :: Developers
Classifier: Intended Audience :: Science/Research
Classifier: License :: OSI Approved :: GNU General Public License v2 (GPLv2)
Classifier: Operating System :: POSIX :: Linux
Classifier: Topic :: System :: Networking
Classifier: Programming Language :: Python :: 3
Requires-Python: >=3.5
Requires-Dist: pyroute2
